data/__init__.py
data/node_control.conf
data/nssm_original.exe
data/migrations/README.md
data/migrations/__init__.py
data/migrations/deb/1_0_96_to_1_0_97.py
data/migrations/deb/1_1_150_to_1_1_151.py
data/migrations/deb/1_2_188_to_1_2_189.py
data/migrations/deb/1_2_233_to_1_2_234.py
data/migrations/deb/1_2_273_to_1_2_274.py
data/migrations/deb/1_3_396_to_1_3_397.py
data/migrations/deb/1_3_428_to_1_3_429.py
data/migrations/deb/1_3_433_to_1_3_434.py
data/migrations/deb/1_4_500_to_1_4_501.py
data/migrations/deb/1_6_703_to_1_6_704.py
data/migrations/deb/1_9_1_to_1_9_2.py
data/migrations/deb/__init__.py
data/migrations/deb/disabled_1_0_97_to_1_0_96.py
data/migrations/deb/helper_1_0_96_to_1_0_97.py
home/runner/.indy/nssm_original.exe
indicio_indy_node-1.13.3rc4.data/scripts/clear_node.py
indicio_indy_node-1.13.3rc4.data/scripts/complete_rebranding_upgrade_ubuntu1604.sh
indicio_indy_node-1.13.3rc4.data/scripts/create_dirs.sh
indicio_indy_node-1.13.3rc4.data/scripts/current_validators
indicio_indy_node-1.13.3rc4.data/scripts/delete_indy_node.bat
indicio_indy_node-1.13.3rc4.data/scripts/generate_bls_proof_of_possession
indicio_indy_node-1.13.3rc4.data/scripts/generate_indy_pool_transactions
indicio_indy_node-1.13.3rc4.data/scripts/get_keys
indicio_indy_node-1.13.3rc4.data/scripts/get_metrics
indicio_indy_node-1.13.3rc4.data/scripts/init_bls_keys
indicio_indy_node-1.13.3rc4.data/scripts/init_indy_keys
indicio_indy_node-1.13.3rc4.data/scripts/install_indy_node.bat
indicio_indy_node-1.13.3rc4.data/scripts/install_nssm.bat
indicio_indy_node-1.13.3rc4.data/scripts/node_address_list
indicio_indy_node-1.13.3rc4.data/scripts/nscapture
indicio_indy_node-1.13.3rc4.data/scripts/nsdiff
indicio_indy_node-1.13.3rc4.data/scripts/nsreplay
indicio_indy_node-1.13.3rc4.data/scripts/read_ledger
indicio_indy_node-1.13.3rc4.data/scripts/restart_indy_node.bat
indicio_indy_node-1.13.3rc4.data/scripts/restart_indy_node_ubuntu1604.sh
indicio_indy_node-1.13.3rc4.dist-info/LICENSE
indicio_indy_node-1.13.3rc4.dist-info/METADATA
indicio_indy_node-1.13.3rc4.dist-info/WHEEL
indicio_indy_node-1.13.3rc4.dist-info/top_level.txt
indicio_indy_node-1.13.3rc4.dist-info/RECORD
