Metadata-Version: 2.1
Name: indicio-indy-node
Version: 1.13.3rc4
Summary: Indy node
Home-page: https://github.com/Indicio-tech/indy-node
Author: Hyperledger
Author-email: hyperledger-indy@lists.hyperledger.org
Maintainer: Indicio
License: Apache 2.0
Keywords: Indy Node
Classifier: Programming Language :: Python :: 3
License-File: LICENSE
Requires-Dist: indicio-indy-plenum==1.13.2-rc20
Requires-Dist: importlib-metadata==3.10.1
Requires-Dist: timeout-decorator>=0.5.0
Requires-Dist: distro==1.7.0
Provides-Extra: tests
Requires-Dist: attrs>=20.3.0; extra == "tests"
Requires-Dist: pytest>=6.2.2; extra == "tests"
Requires-Dist: pytest-xdist>=2.2.1; extra == "tests"
Requires-Dist: pytest-forked>=1.3.0; extra == "tests"
Requires-Dist: python3-indy==1.16.0.post236; extra == "tests"
Requires-Dist: pytest-asyncio>=0.14.0; extra == "tests"
